labneura.cpython-311-darwin.so
labneura-0.0.11.dist-info/LICENSE
labneura-0.0.11.dist-info/METADATA
labneura-0.0.11.dist-info/WHEEL
labneura-0.0.11.dist-info/top_level.txt
labneura-0.0.11.dist-info/RECORD
