Metadata-Version: 2.1
Name: labneura
Version: 0.0.11
Summary: Python package for ML and EDA functionalities with C++ backend
Author: Tharun Kumar Goka
Author-email: tharunkumargoka2020@gmail.com
License-File: LICENSE
